{
    "etag": "W/\"dcec782a1e84ac84b2a5d41e4784665d8397ca720b3f51460887fa29fa0b8465\"",
    "modified": "",
    "last_entry_id": "https://www.bibliaon.com/salmos_74/",
    "https://www.bibliaon.com/salmos_74/": true,
    "https://www.bibliaon.com/salmos_55/": true,
    "https://www.bibliaon.com/salmos_120/": true,
    "https://www.bibliaon.com/salmos_111/": true,
    "https://www.bibliaon.com/salmos_63/": true,
    "https://www.bibliaon.com/salmos_21/": true,
    "https://www.bibliaon.com/salmos_146/": true,
    "https://www.bibliaon.com/salmos_86/": true,
    "https://www.bibliaon.com/salmos_138/": true,
    "https://www.bibliaon.com/salmos_64/": true,
    "https://www.bibliaon.com/salmos_97/": true,
    "https://www.bibliaon.com/salmos_121/": true,
    "https://www.bibliaon.com/salmos_60/": true,
    "https://www.bibliaon.com/salmos_76/": true,
    "https://www.bibliaon.com/salmos_109/": true
}